sramHD_64x64.v
module sramHD_64x64 (
    input  wire        CLK,
    input  wire        ME,  // Memory Enable
    input  wire        WE,  // Write Enable
    input  wire [5:0]  ADR, // 64 words = 6-bit address
    input  wire [63:0] D,   // Data in
    output reg  [63:0] Q    // Data out
);
    reg [63:0] mem_core_array [0:63];

    // Declare loop variable for initialization
    integer j;

    // Initialize memory array and output to 0 at time 0
    initial begin
        for (j = 0; j < 64; j = j + 1) begin
            mem_core_array[j] = 64'h0;
        end
        Q = 64'h0;
    end

    // Clocked Read / Write Logic
    always @(posedge CLK) begin
        if (ME) begin
            if (WE)
                mem_core_array[ADR] <= D;
            else
                Q <= mem_core_array[ADR];
        end
    end

endmodule

mult_32b.v
// File: mult_32b.v
// Description: 32-bit Multiplier unit
// ============================================================================
module mult_32b (
    input  wire        clk,
    input  wire        rst,
    input  wire        start,
    input  wire [1:0]  cmd,
    input  wire [63:0] op1,
    input  wire [63:0] op2,
    output reg  [63:0] res,
    output reg         done
);

    always @(posedge clk or posedge rst) begin
        if (rst) begin
            res       <= 64'd0;
            done      <= 1'b0;
        end else begin
            done <= 1'b0;
            if (start && (cmd == `CMD_MULT)) begin
                res       <= (op1 * op2);
                done      <= 1'b1;
            end
        end
    end

endmodule

// ============================================================================

ALU_32b.v
// File: ALU_32b.v
// Description: 32-bit Addition/Subtraction unit
// ============================================================================
module addsub_32b (
    input  wire        clk,
    input  wire        rst,
    input  wire        en_ALU,
    input  wire [1:0]  cmd,
    input  wire [63:0] op1,
    input  wire [63:0] op2,
    output reg  [63:0] res,
    output reg         done
);

    always @(posedge clk or posedge rst) begin
        if (rst) begin
            res  <= 64'd0;
            done <= 1'b0;
        end else begin
            done <= 1'b0;
            if (en_ALU) begin
                case (cmd)
                    `CMD_ADD: begin
                        res  <= op1 + op2;
                        done <= 1'b1;
                    end
                    `CMD_SUB: begin
                        res  <= op1 - op2;
                        done <= 1'b1;
                    end
                    default: begin
                        res  <= 64'd0;
                        done <= 1'b1;
                    end
                endcase
            end
        end
    end

endmodule

// ============================================================================

alu32_pkg.vh
// File: alu32_pkg.vh
// Description: Global constants and definitions for the 32-bit Semicustom ALU
// ============================================================================
`define CMD_NOOP 2'b00
`define CMD_ADD  2'b01
`define CMD_SUB  2'b10
`define CMD_MULT 2'b11

`define ARRAY_SEL0 2'b00
`define ARRAY_SEL1 2'b01
`define ARRAY_SEL2 2'b10
`define ARRAY_NONE 2'b11

// ============================================================================

top_scheduler.v
// File: top_scheduler.v
// Description: Central FSM controller for sequence scheduling and memory routing
// ============================================================================
`include "alu32_pkg.vh"

module top_scheduler (
    input  wire        clk,
    input  wire        rst,
    input  wire        alu_compute_start,
    input  wire        alu_done,
    input  wire        mult_done,
    output reg  [1:0]  cmd_out,
    input  wire [2:0]  current_instruction_cmd,
    output reg         en_addsub,
    output reg         en_mult,
    output reg  [1:0]  array_select,
    output reg  [5:0]  mem_addr,
    output reg         mem_we,
    output reg         mem_me,
    output reg  [2:0]  state_current,
    output reg         wr_mem_start,
    output reg         wr_mem2_start
);
    // FSM States
    localparam IDLE        = 3'd0,
               READ_MEMS   = 3'd1,
               WAIT_MEM    = 3'd2,
               EXECUTE     = 3'd3,
               WRITE_MEM2  = 3'd4;

    reg [2:0] state_next;
    reg [5:0] reg_counter;

    // Sequential State & Address Counter Logic
    always @(posedge clk or posedge rst) begin
        if (rst) begin
            state_current <= IDLE;
            reg_counter   <= 6'd0;
        end else begin
            state_current <= state_next;
            if (state_current == WRITE_MEM2)
                reg_counter <= reg_counter + 1'b1;
        end
    end

    // Combinatorial Next-State and Output Logic
    always @(*) begin
        // Default outputs
        state_next    = state_current;
        cmd_out       = `CMD_NOOP;
        en_addsub     = 1'b0;
        en_mult       = 1'b0;
        array_select  = `ARRAY_NONE;
        mem_we        = 1'b0;
        mem_me        = 1'b0;
        mem_addr      = reg_counter;
        wr_mem_start  = 1'b0;
        wr_mem2_start = 1'b0;

        case (state_current)
            IDLE: begin
                if (alu_compute_start)
                    state_next = READ_MEMS;
            end

            READ_MEMS: begin
                mem_me     = 1'b0;
                mem_we     = 1'b0; 
                state_next = WAIT_MEM;
            end
            
            WAIT_MEM: begin
                mem_me     = 1'b1;
                state_next = EXECUTE;
            end

            EXECUTE: begin
                cmd_out = current_instruction_cmd;
                mem_me        = 1'b1;
                mem_we        = 1'b1;
                array_select  = `ARRAY_SEL2;

                if (cmd_out == `CMD_MULT)
                    en_mult = 1'b1;
                else
                    en_addsub = 1'b1;
                    
                if (alu_done || mult_done) begin
                    state_next = WRITE_MEM2;
                end
            end

            WRITE_MEM2: begin
                // Drive ME and WE to SRAM MEM2
                array_select  = `ARRAY_SEL2;
                state_next    = IDLE;
            end

            default: state_next = IDLE;
        endcase
    end
endmodule

top_32b.v
// File: top_32b.v
// Description: Top-level integration matching Control Registers, SRAMs, ALU, MULT, and Scheduler
// ============================================================================
module top_32b (
    input  wire        clk,
    input  wire        rst,
    input  wire        global_en,
    input  wire        alu_compute_start,
    input  wire        rd_mem_start,
    input  wire        wr_mem_start,
    input  wire [1:0]  array_select,
    input  wire [1:0]  cmd_top,       // Control and Status Register input
    input  wire        mode_top,      // Control and Status Register input
    input  wire [63:0] data_in_top,
    input  wire [2:0]  current_instruction_cmd,
    output wire [63:0] pin_data_out_mem0,
    output wire [63:0] pin_data_out_mem1,
    output wire [63:0] pin_data_out_mem2,
    output wire        wr_mem2_start
);

    // Gated Clocking
    wire gated_clk = clk & global_en;

    // ============================================================
    // Control & Status Registers Interconnects
    // ============================================================
    reg [1:0] reg_cmd;
    reg       reg_mode;

    always @(posedge clk or posedge rst) begin
        if (rst) begin
            reg_cmd  <= 2'b00;
            reg_mode <= 1'b0;
        end else begin
            reg_cmd  <= cmd_top;
            reg_mode <= mode_top;
        end
    end

    // ============================================================
    // Scheduler Interconnect Wires
    // ============================================================
    wire [1:0]  scheduler_cmd;
    wire [1:0]  scheduler_array_select;
    wire [5:0]  scheduler_mem_addr;
    wire        scheduler_mem_we;
    wire        scheduler_mem_me;
    wire        en_addsub;
    wire        en_mult;
    wire [2:0]  state_current;
    wire        scheduler_wr_mem_start;

    // ============================================================
    // Memory Output & Execution Unit Signals
    // ============================================================
    wire [63:0] mem0_q;
    wire [63:0] mem1_q;
    wire [63:0] mem2_q;
    wire [63:0] alu_res;
    wire [63:0] mult_res;
    wire        alu_done;
    wire        mult_done;

    // ============================================================
    // Host Burst Address Counter (Auto-increments for TB)
    // ============================================================
    reg [5:0] host_addr;

    always @(posedge clk or posedge rst) begin
        if (rst) begin
            host_addr <= 6'd0;
        end else if (wr_mem_start || rd_mem_start) begin
            host_addr <= host_addr + 1'b1;
        end else begin
            host_addr <= 6'd0;
        end
    end

    // ============================================================
    // Host Control vs. Scheduler Control Multiplexing
    // ============================================================
    wire host_active = wr_mem_start || rd_mem_start;

    //wire [5:0] effective_mem_addr = host_active ? host_addr : scheduler_mem_addr;

    reg [5:0] effective_mem_addr;

    always @(posedge clk or posedge rst) begin
        if (rst) begin
            effective_mem_addr = 6'd0;
        end else begin
            effective_mem_addr = host_active ? host_addr : scheduler_mem_addr;
        end
    end

    // Direct synchronization between Scheduler ME/WE and SRAM Memory Instances
    wire mem0_me = host_active ? (array_select == `ARRAY_SEL0) : scheduler_mem_me;
    wire mem1_me = host_active ? (array_select == `ARRAY_SEL1) : scheduler_mem_me;
    wire mem2_me = host_active ? (array_select == `ARRAY_SEL2) : (scheduler_mem_me && (scheduler_array_select == `ARRAY_SEL2));

    wire mem0_we = host_active ? (wr_mem_start && (array_select == `ARRAY_SEL0)) : 1'b0;
    wire mem1_we = host_active ? (wr_mem_start && (array_select == `ARRAY_SEL1)) : 1'b0;
    wire mem2_we = host_active ? (wr_mem_start && (array_select == `ARRAY_SEL2)) : (scheduler_mem_we && (scheduler_array_select == `ARRAY_SEL2));

    // ============================================================
    // Input Data Demultiplexer
    // ============================================================
    wire [63:0] data_in_mem0      = (wr_mem_start && (array_select == `ARRAY_SEL0)) ? data_in_top : 64'h0;
    wire [63:0] data_in_mem1      = (wr_mem_start && (array_select == `ARRAY_SEL1)) ? data_in_top : 64'h0;

    // ============================================================
    // Result MUX & MEM2 Input MUX
    // ============================================================
    wire [63:0] res_sel_out = (scheduler_cmd == `CMD_MULT) ? mult_res : alu_res;

    wire [63:0] data_in_mem2 = (wr_mem_start && (array_select == `ARRAY_SEL2)) 
                             ? data_in_top 
                             : res_sel_out;

    // ============================================================
    // Submodule Instantiations
    // ============================================================

    top_scheduler I_TOP_SCHEDULER (
        .clk                     (clk),
        .rst                     (rst),
        .alu_compute_start       (alu_compute_start),
        .alu_done                (alu_done),
        .mult_done               (mult_done),
        .cmd_out                 (scheduler_cmd),
        .current_instruction_cmd (current_instruction_cmd),
        .en_addsub               (en_addsub),
        .en_mult                 (en_mult),
        .array_select            (scheduler_array_select),
        .mem_addr                (scheduler_mem_addr),
        .mem_we                  (scheduler_mem_we),
        .mem_me                  (scheduler_mem_me),
        .state_current           (state_current),
        .wr_mem_start            (scheduler_wr_mem_start),
        .wr_mem2_start           (wr_mem2_start)
    );

    addsub_32b I_ADDSUB (
        .clk    (gated_clk),
        .rst    (rst),
        .en_ALU (en_addsub),
        .cmd    (scheduler_cmd),
        .op1    (mem0_q),
        .op2    (mem1_q),
        .res    (alu_res),
        .done   (alu_done)
    );

    mult_32b I_MULT (
        .clk    (gated_clk),
        .rst    (rst),
        .start  (en_mult),
        .cmd    (scheduler_cmd),
        .op1    (mem0_q),
        .op2    (mem1_q),
        .res    (mult_res),
        .done   (mult_done)
    );

    sramHD_64x64 MEM0 (
        .CLK (gated_clk),
        .ME  (mem0_me),
        .WE  (mem0_we),
        .ADR (effective_mem_addr),
        .D   (data_in_mem0),
        .Q   (mem0_q)
    );

    sramHD_64x64 MEM1 (
        .CLK (gated_clk),
        .ME  (mem1_me),
        .WE  (mem1_we),
        .ADR (effective_mem_addr),
        .D   (data_in_mem1),
        .Q   (mem1_q)
    );

    sramHD_64x64 MEM2 (
        .CLK (gated_clk),
        .ME  (mem2_me),
        .WE  (mem2_we),
        .ADR (effective_mem_addr),
        .D   (data_in_mem2),
        .Q   (mem2_q)
    );

    assign pin_data_out_mem0 = mem0_q;
    assign pin_data_out_mem1 = mem1_q;
    assign pin_data_out_mem2 = mem2_q;

endmodule

top_32b_tb.v
`timescale 1ns/1ps

module top_32b_tb;

    // Clock and Global Control
    reg        clk;
    reg        rst;
    reg        global_en;

    // Scheduler / Top Commands
    reg        alu_compute_start;
    reg        rd_mem_start;
    reg        wr_mem_start;

    reg [1:0]  array_select;
    reg [1:0]  cmd_top;
    reg        mode_top;
    reg [2:0] tb_instruction_cmd;

    // Data Buses
    reg  [63:0] data_in_top;
    wire [63:0] pin_data_out_mem0;
    wire [63:0] pin_data_out_mem1;
    wire [63:0] pin_data_out_mem2;

    wire wr_mem2_start;

    // Testbench memory arrays declared outside procedural blocks
    reg [63:0] mem0_test_data [0:15];
    reg [63:0] mem1_test_data [0:15];

    reg [2:0] test_instructions [0:15];
    

    parameter T = 10; // 100 MHz clock period

    // UUT Instance
    top_32b uut (
        .clk               (clk),
        .rst               (rst),
        .global_en         (global_en),
        .alu_compute_start (alu_compute_start),
        .rd_mem_start      (rd_mem_start),
        .wr_mem_start      (wr_mem_start),
        .array_select      (array_select),
        .cmd_top           (cmd_top),    // Connected
        .mode_top          (mode_top),   // Connected
        .data_in_top       (data_in_top),
        .pin_data_out_mem0 (pin_data_out_mem0),
        .pin_data_out_mem1 (pin_data_out_mem1),
        .pin_data_out_mem2 (pin_data_out_mem2),
        .current_instruction_cmd (tb_instruction_cmd),
        .wr_mem2_start (wr_mem2_start)
    );

    
    // Continuous Clock Generation
    always #(T/2) clk = ~clk;

    integer i;

    initial begin
        $dumpfile("top_32b_tb.vcd");
        $dumpvars(0, top_32b_tb);

        // ====================================================================
        // PHASE 1: Testbench Init
        // ====================================================================
        clk               = 0;
        rst               = 1;
        global_en         = 0;
        alu_compute_start = 0;
        rd_mem_start      = 0;
        wr_mem_start      = 0;
        array_select      = 2'b11; // ARRAY_NONE
        cmd_top           = 2'b00;
        mode_top          = 0;
        data_in_top       = 64'h0;

        #(2.5 * T);
        rst       = 0;
        global_en = 1;
        #(T);

        // ====================================================================
        // STIMULUS MEMORY ARRAYS (Table 16 Operations Data)
        // ====================================================================
       

        // Populate Operand 0 and Operand 1 arrays
        mem0_test_data[0]  = 64'h0000_0000_0000_000F; mem1_test_data[0]  = 64'h0000_0000_0000_00F0; // ADD
        mem0_test_data[1]  = 64'h0000_0000_0000_0000; mem1_test_data[1]  = 64'h0000_0000_0000_0000; // MULT
        mem0_test_data[2]  = 64'h0000_FFFF_0000_0000; mem1_test_data[2]  = 64'h0000_0000_FFFF_0000; // ADD
        mem0_test_data[3]  = 64'h0000_0000_FFFF_FFFF; mem1_test_data[3]  = 64'h0000_0000_FFFF_FFFF; // SUB
        mem0_test_data[4]  = 64'h0000_0000_FFFF_FFFF; mem1_test_data[4]  = 64'h0000_0000_0000_0000; // NOOP
        mem0_test_data[5]  = 64'h0000_0000_FFFF_FFFF; mem1_test_data[5]  = 64'h0000_0000_FFFF_FFFF; // MULT
        mem0_test_data[6]  = 64'h0000_0000_0000_000F; mem1_test_data[6]  = 64'h0000_0000_0000_000F; // MULT
        mem0_test_data[7]  = 64'h0000_0000_0000_0000; mem1_test_data[7]  = 64'h0000_0000_0000_0000; // MULT
        mem0_test_data[8]  = 64'h0000_0000_0000_FFFF; mem1_test_data[8]  = 64'h0000_0000_0000_FFFF; // MULT
        mem0_test_data[9]  = 64'h0000_0000_0000_0000; mem1_test_data[9]  = 64'h0000_0000_0000_0000; // MULT
        mem0_test_data[10] = 64'h0000_0000_0FFF_FFFF; mem1_test_data[10] = 64'h0000_0000_0FFF_FFFF; // MULT
        mem0_test_data[11] = 64'h0000_0000_0000_0000; mem1_test_data[11] = 64'h0000_0000_0000_0000; // MULT
        mem0_test_data[12] = 64'h0000_0000_FFFF_FFFF; mem1_test_data[12] = 64'h0000_0000_FFFF_FF00; // MULT
        mem0_test_data[13] = 64'h0000_0000_0000_0000; mem1_test_data[13] = 64'h0000_0000_0000_0000; // MULT
        mem0_test_data[14] = 64'h0000_0000_FFFF_FFFF; mem1_test_data[14] = 64'h0000_0000_FFFF_FFFF; // MULT
        mem0_test_data[15] = 64'h0000_0000_0000_0000; mem1_test_data[15] = 64'h0000_0000_0000_0000; // MULT
    

        test_instructions[0]  = `CMD_ADD;  // 000000000000000F + 00000000000000F0
        test_instructions[1]  = `CMD_MULT; // 0000000000000000 * 0000000000000000
        test_instructions[2]  = `CMD_ADD;  // 0000FFFF00000000 + 00000000FFFF0000
        test_instructions[3]  = `CMD_SUB;  // 00000000FFFFFFFF - 00000000FFFFFFFF -> 0x0
        test_instructions[4]  = `CMD_ADD;  // NOOP / Default ADD
        test_instructions[5]  = `CMD_MULT; // 00000000FFFFFFFF * 00000000FFFFFFFF
        test_instructions[6]  = `CMD_MULT; // 000000000000000F * 000000000000000F
        test_instructions[7]  = `CMD_MULT; // 0000000000000000 * 0000000000000000
        test_instructions[8]  = `CMD_MULT; // 000000000000FFFF * 000000000000FFFF
        test_instructions[9]  = `CMD_MULT; // 0000000000000000 * 0000000000000000
        test_instructions[10] = `CMD_MULT; // 000000000FFF_FFFF * 000000000FFF_FFFF
        test_instructions[11] = `CMD_MULT; // 0000000000000000 * 0000000000000000
        test_instructions[12] = `CMD_MULT; // 00000000FFFFFFFF * 00000000FFFFFF00
        test_instructions[13] = `CMD_MULT; // 0000000000000000 * 0000000000000000
        test_instructions[14] = `CMD_MULT; // 00000000FFFFFFFF * 00000000FFFFFFFF
        test_instructions[15] = `CMD_MULT; // 0000000000000000 * 0000000000000000   


    // ====================================================================
    // PHASE 1: Write to MEM0 (Populate Operand 0 Array)
    // ====================================================================
    array_select = 2'b00;
    wr_mem_start = 1;


    for (i = 0; i < 16; i = i + 1) begin
        data_in_top = mem0_test_data[i];
        #(T);
    end
    
    wr_mem_start = 0;
    array_select = 2'b11;
    #(2 * T);

    // ====================================================================
    // PHASE 2: Write to MEM1 (Populate Operand 1 Array)
    // ====================================================================
    array_select = 2'b01; // Select MEM1
    wr_mem_start = 1;

    for (i = 0; i < 16; i = i + 1) begin
        data_in_top = mem1_test_data[i];
        #(T);
    end
    
    wr_mem_start = 0;
    array_select = 2'b11;
    #(2 * T);

    // ====================================================================
    // PHASE 3: Execute ALU Computation Sequence
    // ====================================================================
    // Testbench Instruction Array
    

    // Reset and initialization sequences...
    alu_compute_start = 1'b0;
    tb_instruction_cmd = `CMD_ADD;

    // Wait for reset to complete
    wait(!rst);
    #20;

    $display("--- Starting Step-by-Step Hardware Execution ---");
    
    
      
    for (i = 0; i < 16; i = i + 1) begin


        // 1. Set command for current operation BEFORE start pulse
        @(posedge clk);
        tb_instruction_cmd = test_instructions[i];

        // 2. Pulse alu_compute_start high for exactly 1 clock cycle
        alu_compute_start = 1'b1;
        @(posedge clk);
        alu_compute_start = 1'b0;

        // 3a. WAIT for FSM to leave IDLE (state_current != 0)
        @(posedge clk);

        // 3. Wait for FSM to finish and return TO IDLE (3'd0)
        while (uut.I_TOP_SCHEDULER.state_current != 3'd0) begin
            @(posedge clk);
            $display("another one %3b ",uut.I_TOP_SCHEDULER.state_current);
        end

        $display("Completed Op %0d with Cmd %b", i, test_instructions[i]);
        #10; // Brief pause between operations
    end 

    $display("--- All 16 Operations Completed ---");
    
    // Wait for SCHEDULER to complete all 16 operations & writes to MEM2
    // Adjust total cycles depending on Multiplier/ALU execution latency


    // ====================================================================
    // PHASE 4: Read from MEM2 (Burst Read Results)
    // ====================================================================
    $display("--- Starting MEM2 Burst Read Phase ---");
    
    // Step 1: Drive read control signals
    array_select = 2'b10; // ARRAY_SEL2 (MEM2)
    rd_mem_start = 1'b1;  // host_active = 1, host_addr = 0

    // Step 2: Wait 1 cycle for SRAM read pipeline latency (Address 0 latched -> Q updated)
    @(posedge clk);
    // Step 2: Wait 1 cycle for SRAM read pipeline latency (Address 0 latched -> Q updated)
    @(posedge clk);

    // Step 3: Loop 16 cycles to display data as host_addr increments 0 -> 15
    for (i = 0; i < 16; i = i + 1) begin
        $display("[Read MEM2] Address: 0x%02h | Data Out: 0x%16h", i, pin_data_out_mem2);
        @(posedge clk);
    end

    // Step 4: Deassert host controls
    rd_mem_start = 1'b0;
    array_select = 2'b11; // ARRAY_NONE
    
    #(5 * T);

    $display("Full 4-phase testbench execution completed successfully.");
    $finish;
end

endmodule

top_32b_tb.vcd
$date
	Thu Oct  8 02:22:45 2026
$end
$version
	Icarus Verilog
$end
$timescale
	1ps
$end
$scope module top_32b_tb $end
$var wire 1 ! wr_mem2_start $end
$var wire 64 " pin_data_out_mem2 [63:0] $end
$var wire 64 # pin_data_out_mem1 [63:0] $end
$var wire 64 $ pin_data_out_mem0 [63:0] $end
$var parameter 32 % T $end
$var reg 1 & alu_compute_start $end
$var reg 2 ' array_select [1:0] $end
$var reg 1 ( clk $end
$var reg 2 ) cmd_top [1:0] $end
$var reg 64 * data_in_top [63:0] $end
$var reg 1 + global_en $end
$var reg 1 , mode_top $end
$var reg 1 - rd_mem_start $end
$var reg 1 . rst $end
$var reg 3 / tb_instruction_cmd [2:0] $end
$var reg 1 0 wr_mem_start $end
$var integer 32 1 i [31:0] $end
$scope module uut $end
$var wire 1 & alu_compute_start $end
$var wire 2 2 array_select [1:0] $end
$var wire 1 ( clk $end
$var wire 2 3 cmd_top [1:0] $end
$var wire 3 4 current_instruction_cmd [2:0] $end
$var wire 64 5 data_in_top [63:0] $end
$var wire 1 6 gated_clk $end
$var wire 1 + global_en $end
$var wire 1 7 host_active $end
$var wire 1 , mode_top $end
$var wire 64 8 pin_data_out_mem0 [63:0] $end
$var wire 64 9 pin_data_out_mem1 [63:0] $end
$var wire 64 : pin_data_out_mem2 [63:0] $end
$var wire 1 - rd_mem_start $end
$var wire 1 . rst $end
$var wire 1 0 wr_mem_start $end
$var wire 1 ! wr_mem2_start $end
$var wire 3 ; state_current [2:0] $end
$var wire 1 < scheduler_wr_mem_start $end
$var wire 1 = scheduler_mem_we $end
$var wire 1 > scheduler_mem_me $end
$var wire 6 ? scheduler_mem_addr [5:0] $end
$var wire 2 @ scheduler_cmd [1:0] $end
$var wire 2 A scheduler_array_select [1:0] $end
$var wire 64 B res_sel_out [63:0] $end
$var wire 64 C mult_res [63:0] $end
$var wire 1 D mult_done $end
$var wire 1 E mem2_we $end
$var wire 64 F mem2_q [63:0] $end
$var wire 1 G mem2_me $end
$var wire 1 H mem1_we $end
$var wire 64 I mem1_q [63:0] $end
$var wire 1 J mem1_me $end
$var wire 1 K mem0_we $end
$var wire 64 L mem0_q [63:0] $end
$var wire 1 M mem0_me $end
$var wire 1 N en_mult $end
$var wire 1 O en_addsub $end
$var wire 64 P data_in_mem2 [63:0] $end
$var wire 64 Q data_in_mem1 [63:0] $end
$var wire 64 R data_in_mem0 [63:0] $end
$var wire 64 S alu_res [63:0] $end
$var wire 1 T alu_done $end
$var reg 6 U effective_mem_addr [5:0] $end
$var reg 6 V host_addr [5:0] $end
$var reg 2 W reg_cmd [1:0] $end
$var reg 1 X reg_mode $end
$scope module I_ADDSUB $end
$var wire 1 6 clk $end
$var wire 1 . rst $end
$var wire 64 Y op2 [63:0] $end
$var wire 64 Z op1 [63:0] $end
$var wire 1 O en_ALU $end
$var wire 2 [ cmd [1:0] $end
$var reg 1 T done $end
$var reg 64 \ res [63:0] $end
$upscope $end
$scope module I_MULT $end
$var wire 1 6 clk $end
$var wire 1 . rst $end
$var wire 1 N start $end
$var wire 64 ] op2 [63:0] $end
$var wire 64 ^ op1 [63:0] $end
$var wire 2 _ cmd [1:0] $end
$var reg 1 D done $end
$var reg 64 ` res [63:0] $end
$upscope $end
$scope module I_TOP_SCHEDULER $end
$var wire 1 & alu_compute_start $end
$var wire 1 T alu_done $end
$var wire 1 ( clk $end
$var wire 3 a current_instruction_cmd [2:0] $end
$var wire 1 D mult_done $end
$var wire 1 . rst $end
$var parameter 3 b EXECUTE $end
$var parameter 3 c IDLE $end
$var parameter 3 d READ_MEMS $end
$var parameter 3 e WAIT_MEM $end
$var parameter 3 f WRITE_MEM2 $end
$var reg 2 g array_select [1:0] $end
$var reg 2 h cmd_out [1:0] $end
$var reg 1 O en_addsub $end
$var reg 1 N en_mult $end
$var reg 6 i mem_addr [5:0] $end
$var reg 1 > mem_me $end
$var reg 1 = mem_we $end
$var reg 6 j reg_counter [5:0] $end
$var reg 3 k state_current [2:0] $end
$var reg 3 l state_next [2:0] $end
$var reg 1 ! wr_mem2_start $end
$var reg 1 < wr_mem_start $end
$upscope $end
$scope module MEM0 $end
$var wire 6 m ADR [5:0] $end
$var wire 1 6 CLK $end
$var wire 64 n D [63:0] $end
$var wire 1 M ME $end
$var wire 1 K WE $end
$var reg 64 o Q [63:0] $end
$var integer 32 p j [31:0] $end
$upscope $end
$scope module MEM1 $end
$var wire 6 q ADR [5:0] $end
$var wire 1 6 CLK $end
$var wire 64 r D [63:0] $end
$var wire 1 J ME $end
$var wire 1 H WE $end
$var reg 64 s Q [63:0] $end
$var integer 32 t j [31:0] $end
$upscope $end
$scope module MEM2 $end
$var wire 6 u ADR [5:0] $end
$var wire 1 6 CLK $end
$var wire 64 v D [63:0] $end
$var wire 1 G ME $end
$var wire 1 E WE $end
$var reg 64 w Q [63:0] $end
$var integer 32 x j [31:0] $end
$upscope $end
$upscope $end
$upscope $end
$enddefinitions $end
$comment Show the parameter values. $end
$dumpall
b100 f
b10 e
b1 d
b0 c
b11 b
b1010 %
$end
#0
$dumpvars
b1000000 x
b0 w
b0 v
b0 u
b1000000 t
b0 s
b0 r
b0 q
b1000000 p
b0 o
b0 n
b0 m
b0 l
b0 k
b0 j
b0 i
b0 h
b11 g
bx a
b0 `
b0 _
b0 ^
b0 ]
b0 \
b0 [
b0 Z
b0 Y
0X
b0 W
b0 V
b0 U
0T
b0 S
b0 R
b0 Q
b0 P
0O
0N
0M
b0 L
0K
0J
b0 I
0H
0G
b0 F
0E
0D
b0 C
b0 B
b11 A
b0 @
b0 ?
0>
0=
0<
b0 ;
b0 :
b0 9
b0 8
07
06
b0 5
bx 4
b0 3
b11 2
bx 1
00
bx /
1.
0-
0,
0+
b0 *
b0 )
0(
b11 '
0&
b0 $
b0 #
b0 "
0!
$end
#5000
1(
#10000
0(
#15000
1(
#20000
0(
#25000
16
1(
1+
0.
#30000
06
0(
#35000
b1 V
1M
1K
b1111 R
b1111 n
16
17
1(
b1111 *
b1111 5
b0 1
10
b0 '
b0 2
#40000
06
0(
#45000
b10 V
16
b1 U
b1 m
b1 q
b1 u
b0 R
b0 n
1(
b0 *
b0 5
b1 1
#50000
06
0(
#55000
b11 V
16
b10 U
b10 m
b10 q
b10 u
b111111111111111100000000000000000000000000000000 R
b111111111111111100000000000000000000000000000000 n
1(
b111111111111111100000000000000000000000000000000 *
b111111111111111100000000000000000000000000000000 5
b10 1
#60000
06
0(
#65000
b100 V
16
b11 U
b11 m
b11 q
b11 u
b11111111111111111111111111111111 R
b11111111111111111111111111111111 n
1(
b11111111111111111111111111111111 *
b11111111111111111111111111111111 5
b11 1
#70000
06
0(
#75000
b101 V
16
b100 U
b100 m
b100 q
b100 u
1(
b100 1
#80000
06
0(
#85000
b110 V
16
b101 U
b101 m
b101 q
b101 u
1(
b101 1
#90000
06
0(
#95000
b111 V
16
b110 U
b110 m
b110 q
b110 u
b1111 R
b1111 n
1(
b1111 *
b1111 5
b110 1
#100000
06
0(
#105000
b1000 V
16
b111 U
b111 m
b111 q
b111 u
b0 R
b0 n
1(
b0 *
b0 5
b111 1
#110000
06
0(
#115000
b1001 V
16
b1000 U
b1000 m
b1000 q
b1000 u
b1111111111111111 R
b1111111111111111 n
1(
b1111111111111111 *
b1111111111111111 5
b1000 1
#120000
06
0(
#125000
b1010 V
16
b1001 U
b1001 m
b1001 q
b1001 u
b0 R
b0 n
1(
b0 *
b0 5
b1001 1
#130000
06
0(
#135000
b1011 V
16
b1010 U
b1010 m
b1010 q
b1010 u
b1111111111111111111111111111 R
b1111111111111111111111111111 n
1(
b1111111111111111111111111111 *
b1111111111111111111111111111 5
b1010 1
#140000
06
0(
#145000
b1100 V
16
b1011 U
b1011 m
b1011 q
b1011 u
b0 R
b0 n
1(
b0 *
b0 5
b1011 1
#150000
06
0(
#155000
b1101 V
16
b1100 U
b1100 m
b1100 q
b1100 u
b11111111111111111111111111111111 R
b11111111111111111111111111111111 n
1(
b11111111111111111111111111111111 *
b11111111111111111111111111111111 5
b1100 1
#160000
06
0(
#165000
b1110 V
16
b1101 U
b1101 m
b1101 q
b1101 u
b0 R
b0 n
1(
b0 *
b0 5
b1101 1
#170000
06
0(
#175000
b1111 V
16
b1110 U
b1110 m
b1110 q
b1110 u
b11111111111111111111111111111111 R
b11111111111111111111111111111111 n
1(
b11111111111111111111111111111111 *
b11111111111111111111111111111111 5
b1110 1
#180000
06
0(
#185000
b10000 V
16
b1111 U
b1111 m
b1111 q
b1111 u
b0 R
b0 n
1(
b0 *
b0 5
b1111 1
#190000
06
0(
#195000
b0 V
0K
16
b0 U
b0 m
b0 q
b0 u
0M
07
1(
b11 '
b11 2
00
b10000 1
#200000
06
0(
#205000
16
1(
#210000
06
0(
#215000
b1 V
1J
1H
b11110000 Q
b11110000 r
16
17
1(
b11110000 *
b11110000 5
b0 1
10
b1 '
b1 2
#220000
06
0(
#225000
b10 V
16
b1 U
b1 m
b1 q
b1 u
b0 Q
b0 r
1(
b0 *
b0 5
b1 1
#230000
06
0(
#235000
b11 V
16
b10 U
b10 m
b10 q
b10 u
b11111111111111110000000000000000 Q
b11111111111111110000000000000000 r
1(
b11111111111111110000000000000000 *
b11111111111111110000000000000000 5
b10 1
#240000
06
0(
#245000
b100 V
16
b11 U
b11 m
b11 q
b11 u
b11111111111111111111111111111111 Q
b11111111111111111111111111111111 r
1(
b11111111111111111111111111111111 *
b11111111111111111111111111111111 5
b11 1
#250000
06
0(
#255000
b101 V
16
b100 U
b100 m
b100 q
b100 u
b0 Q
b0 r
1(
b0 *
b0 5
b100 1
#260000
06
0(
#265000
b110 V
16
b101 U
b101 m
b101 q
b101 u
b11111111111111111111111111111111 Q
b11111111111111111111111111111111 r
1(
b11111111111111111111111111111111 *
b11111111111111111111111111111111 5
b101 1
#270000
06
0(
#275000
b111 V
16
b110 U
b110 m
b110 q
b110 u
b1111 Q
b1111 r
1(
b1111 *
b1111 5
b110 1
#280000
06
0(
#285000
b1000 V
16
b111 U
b111 m
b111 q
b111 u
b0 Q
b0 r
1(
b0 *
b0 5
b111 1
#290000
06
0(
#295000
b1001 V
16
b1000 U
b1000 m
b1000 q
b1000 u
b1111111111111111 Q
b1111111111111111 r
1(
b1111111111111111 *
b1111111111111111 5
b1000 1
#300000
06
0(
#305000
b1010 V
16
b1001 U
b1001 m
b1001 q
b1001 u
b0 Q
b0 r
1(
b0 *
b0 5
b1001 1
#310000
06
0(
#315000
b1011 V
16
b1010 U
b1010 m
b1010 q
b1010 u
b1111111111111111111111111111 Q
b1111111111111111111111111111 r
1(
b1111111111111111111111111111 *
b1111111111111111111111111111 5
b1010 1
#320000
06
0(
#325000
b1100 V
16
b1011 U
b1011 m
b1011 q
b1011 u
b0 Q
b0 r
1(
b0 *
b0 5
b1011 1
#330000
06
0(
#335000
b1101 V
16
b1100 U
b1100 m
b1100 q
b1100 u
b11111111111111111111111100000000 Q
b11111111111111111111111100000000 r
1(
b11111111111111111111111100000000 *
b11111111111111111111111100000000 5
b1100 1
#340000
06
0(
#345000
b1110 V
16
b1101 U
b1101 m
b1101 q
b1101 u
b0 Q
b0 r
1(
b0 *
b0 5
b1101 1
